{
    "874b048c963ab55b06939c39d59303fb975d323822a4ea48a02ac8dc635ea371": [
        {
            "image_metadata": {
                "repo": "ubuntu",
                "image_tag": "latest",
                "last_updated": "2023-03-16T02:46:37.788343Z",
                "tag_last_pushed": "2023-03-16T02:46:37.788343Z",
                "arch": "arm64",
                "image_digest": "sha256:537da24818633b45fcb65e5285a68c3ec1f3db25f5ae5476a7757bc8dfae92a3",
                "image_status": "active",
                "image_push_date": "2023-03-16T01:44:02.174509Z"
            },
            "image_layers": [
                {
                    "bom-ref": "pkg:layer/./ubuntu%40sha256:537da24818633b45fcb65e5285a68c3ec1f3db25f5ae5476a7757bc8dfae92a3%40sha256:bab8ce5c00ca3ef91e0d3eb4c6e6d6ec7cffa9574c447fd8d54a8d96e7c1c80e@sha256:874b048c963ab55b06939c39d59303fb975d323822a4ea48a02ac8dc635ea371?index=0&ID=ff11d684762ce9bf",
                    "mime-type": "application/vnd.docker.image.rootfs.diff.tar.gzip",
                    "type": "container",
                    "group": "layer",
                    "name": "sha256:874b048c963ab55b06939c39d59303fb975d323822a4ea48a02ac8dc635ea371",
                    "hashes": [
                        {
                            "alg": "SHA-256",
                            "content": "874b048c963ab55b06939c39d59303fb975d323822a4ea48a02ac8dc635ea371"
                        }
                    ],
                    "purl": "pkg:layer/./ubuntu%40sha256:537da24818633b45fcb65e5285a68c3ec1f3db25f5ae5476a7757bc8dfae92a3%40sha256:bab8ce5c00ca3ef91e0d3eb4c6e6d6ec7cffa9574c447fd8d54a8d96e7c1c80e@sha256:874b048c963ab55b06939c39d59303fb975d323822a4ea48a02ac8dc635ea371?index=0",
                    "properties": [
                        {
                            "name": "size",
                            "value": "69208403"
                        },
                        {
                            "name": "CreatedBy",
                            "value": "#(nop) ADD file:79b36308bc382d9cae7197b4cecc21430f4e8f3e8bec3547d0f00bcff7681e60 in / "
                        },
                        {
                            "name": "index",
                            "value": "0"
                        }
                    ]
                }
            ]
        }
    ]
}