{
    "3b986ade15248804527e3b0d5c1fcd7035fc992934ed54c36a29f7fb38279c61": [
        {
            "image_metadata": {
                "repo": "amazonlinux",
                "image_tag": "2.0.20230221.0",
                "last_updated": "2023-03-02T22:55:27.451762Z",
                "tag_last_pushed": "2023-03-02T22:55:27.451762Z",
                "arch": "arm64",
                "image_digest": "sha256:6824ca16a70bc40b8fdd460c6d78d655e76b4fd5bb0514249d9e7db4143434d0",
                "image_status": "active",
                "image_push_date": "2023-03-02T22:55:20.498155Z"
            },
            "image_layers": [
                {
                    "bom-ref": "pkg:layer/./amazonlinux%40sha256:6824ca16a70bc40b8fdd460c6d78d655e76b4fd5bb0514249d9e7db4143434d0%40sha256:0811b41be99f9ca1f6e32d6f11a18d7bef0a796a7d019c57fbda1653e20252a5@sha256:3b986ade15248804527e3b0d5c1fcd7035fc992934ed54c36a29f7fb38279c61?index=0&ID=a3f76d09272262b1",
                    "mime-type": "application/vnd.docker.image.rootfs.diff.tar.gzip",
                    "type": "container",
                    "group": "layer",
                    "name": "sha256:3b986ade15248804527e3b0d5c1fcd7035fc992934ed54c36a29f7fb38279c61",
                    "hashes": [
                        {
                            "alg": "SHA-256",
                            "content": "3b986ade15248804527e3b0d5c1fcd7035fc992934ed54c36a29f7fb38279c61"
                        }
                    ],
                    "purl": "pkg:layer/./amazonlinux%40sha256:6824ca16a70bc40b8fdd460c6d78d655e76b4fd5bb0514249d9e7db4143434d0%40sha256:0811b41be99f9ca1f6e32d6f11a18d7bef0a796a7d019c57fbda1653e20252a5@sha256:3b986ade15248804527e3b0d5c1fcd7035fc992934ed54c36a29f7fb38279c61?index=0",
                    "properties": [
                        {
                            "name": "size",
                            "value": "194539399"
                        },
                        {
                            "name": "CreatedBy",
                            "value": "#(nop) COPY dir:82034448b19235d709c5681caa8414343fb6e1711c03e26721c451fa22d139eb in / "
                        },
                        {
                            "name": "index",
                            "value": "0"
                        }
                    ]
                }
            ]
        }
    ]
}