{
    "4e2bee53ff56533514f90dc26d420d5ba7ba6179d65eb06e0fb1fda029274c52": [
        {
            "image_metadata": {
                "repo": "debian",
                "image_tag": "oldstable-20220912-slim",
                "last_updated": "2022-09-13T04:14:25.875293Z",
                "tag_last_pushed": "2022-09-13T04:14:25.875293Z",
                "arch": "arm64",
                "image_digest": "sha256:ebc67c7234305c089ba6c3fcf5024b8d92b1f675277181bcd24b83a8bb926a65",
                "image_status": "active",
                "image_push_date": "2022-09-13T02:37:30.553103Z"
            },
            "image_layers": [
                {
                    "bom-ref": "pkg:layer/./debian%40sha256:ebc67c7234305c089ba6c3fcf5024b8d92b1f675277181bcd24b83a8bb926a65%40sha256:ce88fcb97746204174de7d4810f50c71151de61c0095a634541d3e801cc39703@sha256:4e2bee53ff56533514f90dc26d420d5ba7ba6179d65eb06e0fb1fda029274c52?index=0&ID=245a7554161f65fa",
                    "mime-type": "application/vnd.docker.image.rootfs.diff.tar.gzip",
                    "type": "container",
                    "group": "layer",
                    "name": "sha256:4e2bee53ff56533514f90dc26d420d5ba7ba6179d65eb06e0fb1fda029274c52",
                    "hashes": [
                        {
                            "alg": "SHA-256",
                            "content": "4e2bee53ff56533514f90dc26d420d5ba7ba6179d65eb06e0fb1fda029274c52"
                        }
                    ],
                    "purl": "pkg:layer/./debian%40sha256:ebc67c7234305c089ba6c3fcf5024b8d92b1f675277181bcd24b83a8bb926a65%40sha256:ce88fcb97746204174de7d4810f50c71151de61c0095a634541d3e801cc39703@sha256:4e2bee53ff56533514f90dc26d420d5ba7ba6179d65eb06e0fb1fda029274c52?index=0",
                    "properties": [
                        {
                            "name": "size",
                            "value": "63427754"
                        },
                        {
                            "name": "CreatedBy",
                            "value": "#(nop) ADD file:a59bcfb593a1838017e09caae8462f3d003d5160f2fc4ffd9e8b1ee7e24bb08c in / "
                        },
                        {
                            "name": "index",
                            "value": "0"
                        }
                    ]
                }
            ]
        }
    ]
}