{
    "f03597921113d7e778b9b73fe28454fbeb740695e3d357a1595ac22845811305": [
        {
            "image_metadata": {
                "repo": "debian",
                "image_tag": "stable-20210902",
                "last_updated": "2021-09-03T01:53:50.617325Z",
                "tag_last_pushed": "2021-09-03T01:53:50.617325Z",
                "arch": "arm64",
                "image_digest": "sha256:45e16e989f50c52b3826e521d3093458eff48bdc7c4504d8e398f664c00c8eb9",
                "image_status": "active",
                "image_push_date": "2021-09-03T01:20:27.312943Z"
            },
            "image_layers": [
                {
                    "bom-ref": "pkg:layer/./debian%40sha256:45e16e989f50c52b3826e521d3093458eff48bdc7c4504d8e398f664c00c8eb9%40sha256:3a3d87e1521f814b5c3d5344e450acb719a00ae1dd2889aa76a412677a5e9b77@sha256:f03597921113d7e778b9b73fe28454fbeb740695e3d357a1595ac22845811305?index=0&ID=9164c857bed86e6e",
                    "mime-type": "application/vnd.docker.image.rootfs.diff.tar.gzip",
                    "type": "container",
                    "group": "layer",
                    "name": "sha256:f03597921113d7e778b9b73fe28454fbeb740695e3d357a1595ac22845811305",
                    "hashes": [
                        {
                            "alg": "SHA-256",
                            "content": "f03597921113d7e778b9b73fe28454fbeb740695e3d357a1595ac22845811305"
                        }
                    ],
                    "purl": "pkg:layer/./debian%40sha256:45e16e989f50c52b3826e521d3093458eff48bdc7c4504d8e398f664c00c8eb9%40sha256:3a3d87e1521f814b5c3d5344e450acb719a00ae1dd2889aa76a412677a5e9b77@sha256:f03597921113d7e778b9b73fe28454fbeb740695e3d357a1595ac22845811305?index=0",
                    "properties": [
                        {
                            "name": "size",
                            "value": "117819153"
                        },
                        {
                            "name": "CreatedBy",
                            "value": "#(nop) ADD file:5ba2f2fbdce5a6e494877ea34b03b0003037f1040019ec546d45bc6c6c259ed2 in / "
                        },
                        {
                            "name": "index",
                            "value": "0"
                        }
                    ]
                }
            ]
        }
    ]
}