{
    "4aa52de08328c843b77c35464818074d724d16a177e8a6be255f08ede0957290": [
        {
            "image_metadata": {
                "repo": "debian",
                "image_tag": "buster-20220316",
                "last_updated": "2022-03-17T11:51:38.761575Z",
                "tag_last_pushed": "2022-03-17T11:51:38.761575Z",
                "arch": "arm64",
                "image_digest": "sha256:272ea3972e872b8f689a9b9906bb3de9a070a1d85ad1635fedd91ddc18177be0",
                "image_status": "active",
                "image_push_date": "2022-03-17T03:50:14.211424Z"
            },
            "image_layers": [
                {
                    "bom-ref": "pkg:layer/./debian%40sha256:272ea3972e872b8f689a9b9906bb3de9a070a1d85ad1635fedd91ddc18177be0%40sha256:21b413cc462ce47ce45fa1e7fbdba759199c1fab45a3a5e65a044e2881d5664f@sha256:4aa52de08328c843b77c35464818074d724d16a177e8a6be255f08ede0957290?index=0&ID=9e6bdb6071047dee",
                    "mime-type": "application/vnd.docker.image.rootfs.diff.tar.gzip",
                    "type": "container",
                    "group": "layer",
                    "name": "sha256:4aa52de08328c843b77c35464818074d724d16a177e8a6be255f08ede0957290",
                    "hashes": [
                        {
                            "alg": "SHA-256",
                            "content": "4aa52de08328c843b77c35464818074d724d16a177e8a6be255f08ede0957290"
                        }
                    ],
                    "purl": "pkg:layer/./debian%40sha256:272ea3972e872b8f689a9b9906bb3de9a070a1d85ad1635fedd91ddc18177be0%40sha256:21b413cc462ce47ce45fa1e7fbdba759199c1fab45a3a5e65a044e2881d5664f@sha256:4aa52de08328c843b77c35464818074d724d16a177e8a6be255f08ede0957290?index=0",
                    "properties": [
                        {
                            "name": "size",
                            "value": "108226324"
                        },
                        {
                            "name": "CreatedBy",
                            "value": "#(nop) ADD file:37cabd1fec04269c22fc158f62ce5bc655934f2e58fb1ff3a1e366a33ba9bc18 in / "
                        },
                        {
                            "name": "index",
                            "value": "0"
                        }
                    ]
                }
            ]
        }
    ]
}