{
    "a5a9d50fda81cf7ce6c87a162a64782c8fc64759cc5111f4742b278f246bfbf7": [
        {
            "image_metadata": {
                "repo": "debian",
                "image_tag": "bookworm-20211220",
                "last_updated": "2021-12-21T02:34:25.710781Z",
                "tag_last_pushed": "2021-12-21T02:34:25.710781Z",
                "arch": "amd64",
                "image_digest": "sha256:3baade3697056cfb82c7e9592d8e1b40eacfebc90e1fe36d39892745822c0f10",
                "image_status": "active",
                "image_push_date": "2021-12-21T01:50:32.196525Z"
            },
            "image_layers": [
                {
                    "bom-ref": "pkg:layer/./debian%40sha256:3baade3697056cfb82c7e9592d8e1b40eacfebc90e1fe36d39892745822c0f10%40sha256:0b63fd03430d8e3ba5bbe108ef16ea978c934a378c865a83af2a040eae9cf174@sha256:a5a9d50fda81cf7ce6c87a162a64782c8fc64759cc5111f4742b278f246bfbf7?index=0&ID=5458581e4205967d",
                    "mime-type": "application/vnd.docker.image.rootfs.diff.tar.gzip",
                    "type": "container",
                    "group": "layer",
                    "name": "sha256:a5a9d50fda81cf7ce6c87a162a64782c8fc64759cc5111f4742b278f246bfbf7",
                    "hashes": [
                        {
                            "alg": "SHA-256",
                            "content": "a5a9d50fda81cf7ce6c87a162a64782c8fc64759cc5111f4742b278f246bfbf7"
                        }
                    ],
                    "purl": "pkg:layer/./debian%40sha256:3baade3697056cfb82c7e9592d8e1b40eacfebc90e1fe36d39892745822c0f10%40sha256:0b63fd03430d8e3ba5bbe108ef16ea978c934a378c865a83af2a040eae9cf174@sha256:a5a9d50fda81cf7ce6c87a162a64782c8fc64759cc5111f4742b278f246bfbf7?index=0",
                    "properties": [
                        {
                            "name": "size",
                            "value": "124997000"
                        },
                        {
                            "name": "CreatedBy",
                            "value": "#(nop) ADD file:15e5b0a35c4fc7a5ae0bf08f713bde738d2cfb06a30b8bd5780fabafb91d934c in / "
                        },
                        {
                            "name": "index",
                            "value": "0"
                        }
                    ]
                }
            ]
        }
    ]
}