{
    "6053e60661c7114f10ee19b242f0dec9d7b14e75247ca1e0195738718219745b": [
        {
            "image_metadata": {
                "repo": "debian",
                "image_tag": "sid-20201117",
                "last_updated": "2020-11-18T01:33:21.397963Z",
                "tag_last_pushed": "2020-11-18T01:33:21.397963Z",
                "arch": "amd64",
                "image_digest": "sha256:363004fa77743c4c20245b7d6445ee8c57af373275cbedd4ed43bac0ea8668df",
                "image_status": "active",
                "image_push_date": "2020-11-18T01:32:57.967152Z"
            },
            "image_layers": [
                {
                    "bom-ref": "pkg:layer/./debian%40sha256:363004fa77743c4c20245b7d6445ee8c57af373275cbedd4ed43bac0ea8668df%40sha256:aa59e8735b59b720217f794fb057656a637a7b3dea9670658e48177d6361bf45@sha256:6053e60661c7114f10ee19b242f0dec9d7b14e75247ca1e0195738718219745b?index=0&ID=80699bf73d458c18",
                    "mime-type": "application/vnd.docker.image.rootfs.diff.tar.gzip",
                    "type": "container",
                    "group": "layer",
                    "name": "sha256:6053e60661c7114f10ee19b242f0dec9d7b14e75247ca1e0195738718219745b",
                    "hashes": [
                        {
                            "alg": "SHA-256",
                            "content": "6053e60661c7114f10ee19b242f0dec9d7b14e75247ca1e0195738718219745b"
                        }
                    ],
                    "purl": "pkg:layer/./debian%40sha256:363004fa77743c4c20245b7d6445ee8c57af373275cbedd4ed43bac0ea8668df%40sha256:aa59e8735b59b720217f794fb057656a637a7b3dea9670658e48177d6361bf45@sha256:6053e60661c7114f10ee19b242f0dec9d7b14e75247ca1e0195738718219745b?index=0",
                    "properties": [
                        {
                            "name": "size",
                            "value": "126792647"
                        },
                        {
                            "name": "CreatedBy",
                            "value": "#(nop) ADD file:e5210ca55e6714aec9564543eeb4b4a748c57e62c0ae0c741dd0f3eb75ab72de in / "
                        },
                        {
                            "name": "index",
                            "value": "0"
                        }
                    ]
                }
            ]
        }
    ]
}