{
    "67a4178b7d47beb6a1f697a593bd0c6841c67eb0da00f2badefb05fd30671490": [
        {
            "image_metadata": {
                "repo": "debian",
                "image_tag": "bullseye-20230109-slim",
                "last_updated": "2023-01-11T17:05:37.447775Z",
                "tag_last_pushed": "2023-01-11T17:05:37.447775Z",
                "arch": "amd64",
                "image_digest": "sha256:1acb06a0c31fb467eb8327ad361f1091ab265e0bf26d452dea45dcb0c0ea5e75",
                "image_status": "active",
                "image_push_date": "2023-01-11T02:45:03.802426Z"
            },
            "image_layers": [
                {
                    "bom-ref": "pkg:layer/./debian%40sha256:1acb06a0c31fb467eb8327ad361f1091ab265e0bf26d452dea45dcb0c0ea5e75%40sha256:9f61210833de8f16b54cacaf517adbd21f2fcf582749390bfc4f35213d55bac3@sha256:67a4178b7d47beb6a1f697a593bd0c6841c67eb0da00f2badefb05fd30671490?index=0&ID=775bcf5d4b222e9d",
                    "mime-type": "application/vnd.docker.image.rootfs.diff.tar.gzip",
                    "type": "container",
                    "group": "layer",
                    "name": "sha256:67a4178b7d47beb6a1f697a593bd0c6841c67eb0da00f2badefb05fd30671490",
                    "hashes": [
                        {
                            "alg": "SHA-256",
                            "content": "67a4178b7d47beb6a1f697a593bd0c6841c67eb0da00f2badefb05fd30671490"
                        }
                    ],
                    "purl": "pkg:layer/./debian%40sha256:1acb06a0c31fb467eb8327ad361f1091ab265e0bf26d452dea45dcb0c0ea5e75%40sha256:9f61210833de8f16b54cacaf517adbd21f2fcf582749390bfc4f35213d55bac3@sha256:67a4178b7d47beb6a1f697a593bd0c6841c67eb0da00f2badefb05fd30671490?index=0",
                    "properties": [
                        {
                            "name": "size",
                            "value": "80479789"
                        },
                        {
                            "name": "CreatedBy",
                            "value": "#(nop) ADD file:e2398d0bf516084b2b37ba1bb76b86d56e66999831df692461679fbd6a5d8eb6 in / "
                        },
                        {
                            "name": "index",
                            "value": "0"
                        }
                    ]
                }
            ]
        }
    ]
}