{
    "0270c2d5ad7267d4e20b234f5252bae2aa22b5fa0742b35a286d70532106269a": [
        {
            "image_metadata": {
                "repo": "debian",
                "image_tag": "buster-20210326-slim",
                "last_updated": "2021-03-26T16:12:03.275159Z",
                "tag_last_pushed": "2021-03-26T16:12:03.275159Z",
                "arch": "amd64",
                "image_digest": "sha256:e9c905e9eb9bc8d490a959d19e92b130d4ca10b84f4848d0c00c33811a23cd4a",
                "image_status": "active",
                "image_push_date": "2021-03-26T15:41:56.53646Z"
            },
            "image_layers": [
                {
                    "bom-ref": "pkg:layer/./debian%40sha256:e9c905e9eb9bc8d490a959d19e92b130d4ca10b84f4848d0c00c33811a23cd4a%40sha256:115566c891d19b02d5d67e428bc0b03fac8789b6fb90cc3afdcb40f57594884c@sha256:0270c2d5ad7267d4e20b234f5252bae2aa22b5fa0742b35a286d70532106269a?index=0&ID=5ae834384e1560d3",
                    "mime-type": "application/vnd.docker.image.rootfs.diff.tar.gzip",
                    "type": "container",
                    "group": "layer",
                    "name": "sha256:0270c2d5ad7267d4e20b234f5252bae2aa22b5fa0742b35a286d70532106269a",
                    "hashes": [
                        {
                            "alg": "SHA-256",
                            "content": "0270c2d5ad7267d4e20b234f5252bae2aa22b5fa0742b35a286d70532106269a"
                        }
                    ],
                    "purl": "pkg:layer/./debian%40sha256:e9c905e9eb9bc8d490a959d19e92b130d4ca10b84f4848d0c00c33811a23cd4a%40sha256:115566c891d19b02d5d67e428bc0b03fac8789b6fb90cc3afdcb40f57594884c@sha256:0270c2d5ad7267d4e20b234f5252bae2aa22b5fa0742b35a286d70532106269a?index=0",
                    "properties": [
                        {
                            "name": "size",
                            "value": "69203045"
                        },
                        {
                            "name": "CreatedBy",
                            "value": "#(nop) ADD file:b2085f4b0a7cb0e5754874c712254e5cd941062b27b8d7ed2080520196b91597 in / "
                        },
                        {
                            "name": "index",
                            "value": "0"
                        }
                    ]
                }
            ]
        }
    ]
}