{
    "3837e0129e4e20b7b0f8cef9e1559b45ca1b4ad6963545087b41869d0c7bb274": [
        {
            "image_metadata": {
                "repo": "debian",
                "image_tag": "jessie-20201117-slim",
                "last_updated": "2020-11-18T01:27:38.16494Z",
                "tag_last_pushed": "2020-11-18T01:27:38.16494Z",
                "arch": "amd64",
                "image_digest": "sha256:ce9eb58ccf85d1fdf3dccaf639afac0e2dbe7c3617b55e2f8c412ac72cbb2fa5",
                "image_status": "active",
                "image_push_date": "2020-11-17T23:21:05.144067Z"
            },
            "image_layers": [
                {
                    "bom-ref": "pkg:layer/./debian%40sha256:ce9eb58ccf85d1fdf3dccaf639afac0e2dbe7c3617b55e2f8c412ac72cbb2fa5%40sha256:f2eeef8fdf1a9ee63cc3dc7ab3c691eb0bda7f9856c11c436b6c951e0a78d9d7@sha256:3837e0129e4e20b7b0f8cef9e1559b45ca1b4ad6963545087b41869d0c7bb274?index=0&ID=60141717a97eee36",
                    "mime-type": "application/vnd.docker.image.rootfs.diff.tar.gzip",
                    "type": "container",
                    "group": "layer",
                    "name": "sha256:3837e0129e4e20b7b0f8cef9e1559b45ca1b4ad6963545087b41869d0c7bb274",
                    "hashes": [
                        {
                            "alg": "SHA-256",
                            "content": "3837e0129e4e20b7b0f8cef9e1559b45ca1b4ad6963545087b41869d0c7bb274"
                        }
                    ],
                    "purl": "pkg:layer/./debian%40sha256:ce9eb58ccf85d1fdf3dccaf639afac0e2dbe7c3617b55e2f8c412ac72cbb2fa5%40sha256:f2eeef8fdf1a9ee63cc3dc7ab3c691eb0bda7f9856c11c436b6c951e0a78d9d7@sha256:3837e0129e4e20b7b0f8cef9e1559b45ca1b4ad6963545087b41869d0c7bb274?index=0",
                    "properties": [
                        {
                            "name": "size",
                            "value": "81328738"
                        },
                        {
                            "name": "CreatedBy",
                            "value": "#(nop) ADD file:53c1c51534ffa778dfc0bd958d74fa6c234f63b1797882d95e988426df8deba1 in / "
                        },
                        {
                            "name": "index",
                            "value": "0"
                        }
                    ]
                }
            ]
        }
    ]
}