{
    "9c4196bffbbce61a8cd4da749e3831ced5c034159face44e6fa30e3bc96f2cc7": [
        {
            "image_metadata": {
                "repo": "debian",
                "image_tag": "unstable-20201209",
                "last_updated": "2020-12-11T04:08:00.658625Z",
                "tag_last_pushed": "2020-12-11T04:08:00.658625Z",
                "arch": "amd64",
                "image_digest": "sha256:d05bbdf433afcdc9bafba74a12f6266b08a94d71ef69d5745d431a2e29614a81",
                "image_status": "active",
                "image_push_date": "2020-12-11T02:51:08.743409Z"
            },
            "image_layers": [
                {
                    "bom-ref": "pkg:layer/./debian%40sha256:d05bbdf433afcdc9bafba74a12f6266b08a94d71ef69d5745d431a2e29614a81%40sha256:4dc6ee322616156aae4d7ce81b3b1668dd60e639a0c84a9ac5982c3b747b1ea3@sha256:9c4196bffbbce61a8cd4da749e3831ced5c034159face44e6fa30e3bc96f2cc7?index=0&ID=af040c40c84cbe93",
                    "mime-type": "application/vnd.docker.image.rootfs.diff.tar.gzip",
                    "type": "container",
                    "group": "layer",
                    "name": "sha256:9c4196bffbbce61a8cd4da749e3831ced5c034159face44e6fa30e3bc96f2cc7",
                    "hashes": [
                        {
                            "alg": "SHA-256",
                            "content": "9c4196bffbbce61a8cd4da749e3831ced5c034159face44e6fa30e3bc96f2cc7"
                        }
                    ],
                    "purl": "pkg:layer/./debian%40sha256:d05bbdf433afcdc9bafba74a12f6266b08a94d71ef69d5745d431a2e29614a81%40sha256:4dc6ee322616156aae4d7ce81b3b1668dd60e639a0c84a9ac5982c3b747b1ea3@sha256:9c4196bffbbce61a8cd4da749e3831ced5c034159face44e6fa30e3bc96f2cc7?index=0",
                    "properties": [
                        {
                            "name": "size",
                            "value": "120739593"
                        },
                        {
                            "name": "CreatedBy",
                            "value": "#(nop) ADD file:0ef8e76cde130d3f049e85bdfac1292f2411a3d65f704e1b3b7775fbe2a4c98f in / "
                        },
                        {
                            "name": "index",
                            "value": "0"
                        }
                    ]
                }
            ]
        }
    ]
}