{
    "876faed73384fc5f4413c6eb8eb5d97c799e8b629066e44b29824959daf13512": [
        {
            "image_metadata": {
                "repo": "debian",
                "image_tag": "stable-20220801-slim",
                "last_updated": "2022-08-02T01:36:53.494047Z",
                "tag_last_pushed": "2022-08-02T01:36:53.494047Z",
                "arch": "amd64",
                "image_digest": "sha256:5c81749f3f9d7366bef750716c0d3f031e1b896518546ec2f77ffd06cb885541",
                "image_status": "active",
                "image_push_date": "2022-08-02T01:36:48.136178Z"
            },
            "image_layers": [
                {
                    "bom-ref": "pkg:layer/./debian%40sha256:5c81749f3f9d7366bef750716c0d3f031e1b896518546ec2f77ffd06cb885541%40sha256:7570191152ed7ff982a3e45280f010b286960c21dcec433b5f7d2f577e09120f@sha256:876faed73384fc5f4413c6eb8eb5d97c799e8b629066e44b29824959daf13512?index=0&ID=1c4a9d9ff141de9a",
                    "mime-type": "application/vnd.docker.image.rootfs.diff.tar.gzip",
                    "type": "container",
                    "group": "layer",
                    "name": "sha256:876faed73384fc5f4413c6eb8eb5d97c799e8b629066e44b29824959daf13512",
                    "hashes": [
                        {
                            "alg": "SHA-256",
                            "content": "876faed73384fc5f4413c6eb8eb5d97c799e8b629066e44b29824959daf13512"
                        }
                    ],
                    "purl": "pkg:layer/./debian%40sha256:5c81749f3f9d7366bef750716c0d3f031e1b896518546ec2f77ffd06cb885541%40sha256:7570191152ed7ff982a3e45280f010b286960c21dcec433b5f7d2f577e09120f@sha256:876faed73384fc5f4413c6eb8eb5d97c799e8b629066e44b29824959daf13512?index=0",
                    "properties": [
                        {
                            "name": "size",
                            "value": "80380385"
                        },
                        {
                            "name": "CreatedBy",
                            "value": "#(nop) ADD file:b34d8752354b3dbdfb42882174511ca6bde6469076cf5c20f65a662b5693f751 in / "
                        },
                        {
                            "name": "index",
                            "value": "0"
                        }
                    ]
                }
            ]
        }
    ]
}