{
    "644c93f2a36a8c038181318ad9d6f152d3929e2166a38eb5a5c8909cb3532696": [
        {
            "image_metadata": {
                "repo": "debian",
                "image_tag": "stretch-20210816-slim",
                "last_updated": "2021-08-17T02:44:24.458301Z",
                "tag_last_pushed": "2021-08-17T02:44:24.458301Z",
                "arch": "amd64",
                "image_digest": "sha256:359cccd94a97f73cfe314e2c328fba4ca742e5fd3543d4c26e1280520930884d",
                "image_status": "active",
                "image_push_date": "2021-08-17T01:45:14.461547Z"
            },
            "image_layers": [
                {
                    "bom-ref": "pkg:layer/./debian%40sha256:359cccd94a97f73cfe314e2c328fba4ca742e5fd3543d4c26e1280520930884d%40sha256:750df3e387d7395e1cdecbddcde5747bc9f97691dc491623e4fefb28a86b89a3@sha256:644c93f2a36a8c038181318ad9d6f152d3929e2166a38eb5a5c8909cb3532696?index=0&ID=a2d96ae185ea5710",
                    "mime-type": "application/vnd.docker.image.rootfs.diff.tar.gzip",
                    "type": "container",
                    "group": "layer",
                    "name": "sha256:644c93f2a36a8c038181318ad9d6f152d3929e2166a38eb5a5c8909cb3532696",
                    "hashes": [
                        {
                            "alg": "SHA-256",
                            "content": "644c93f2a36a8c038181318ad9d6f152d3929e2166a38eb5a5c8909cb3532696"
                        }
                    ],
                    "purl": "pkg:layer/./debian%40sha256:359cccd94a97f73cfe314e2c328fba4ca742e5fd3543d4c26e1280520930884d%40sha256:750df3e387d7395e1cdecbddcde5747bc9f97691dc491623e4fefb28a86b89a3@sha256:644c93f2a36a8c038181318ad9d6f152d3929e2166a38eb5a5c8909cb3532696?index=0",
                    "properties": [
                        {
                            "name": "size",
                            "value": "55321310"
                        },
                        {
                            "name": "CreatedBy",
                            "value": "#(nop) ADD file:f6c4487fa1f7a4e17f5d88fd0c91031a6efc7fa210d363a1d43d8b0f3a8d1d03 in / "
                        },
                        {
                            "name": "index",
                            "value": "0"
                        }
                    ]
                }
            ]
        }
    ]
}