{
    "7b342f49100313ea81457997eaec504a7cfb73e95b0f2afd59d99a4ae861dffc": [
        {
            "image_metadata": {
                "repo": "debian",
                "image_tag": "oldoldstable-20220125",
                "last_updated": "2022-01-26T02:14:17.594297Z",
                "tag_last_pushed": "2022-01-26T02:14:17.594297Z",
                "arch": "amd64",
                "image_digest": "sha256:ec58cf07203ab768b22e96c01bc6b493893d7d820437da8a6e61fb11d0208c06",
                "image_status": "active",
                "image_push_date": "2022-01-26T02:14:07.728888Z"
            },
            "image_layers": [
                {
                    "bom-ref": "pkg:layer/./debian%40sha256:ec58cf07203ab768b22e96c01bc6b493893d7d820437da8a6e61fb11d0208c06%40sha256:5370ea67c1408355bd1ef5f66c109c4ac99c658e5f02f6ecf8ffee035e948a90@sha256:7b342f49100313ea81457997eaec504a7cfb73e95b0f2afd59d99a4ae861dffc?index=0&ID=33d42e5cbaf70f91",
                    "mime-type": "application/vnd.docker.image.rootfs.diff.tar.gzip",
                    "type": "container",
                    "group": "layer",
                    "name": "sha256:7b342f49100313ea81457997eaec504a7cfb73e95b0f2afd59d99a4ae861dffc",
                    "hashes": [
                        {
                            "alg": "SHA-256",
                            "content": "7b342f49100313ea81457997eaec504a7cfb73e95b0f2afd59d99a4ae861dffc"
                        }
                    ],
                    "purl": "pkg:layer/./debian%40sha256:ec58cf07203ab768b22e96c01bc6b493893d7d820437da8a6e61fb11d0208c06%40sha256:5370ea67c1408355bd1ef5f66c109c4ac99c658e5f02f6ecf8ffee035e948a90@sha256:7b342f49100313ea81457997eaec504a7cfb73e95b0f2afd59d99a4ae861dffc?index=0",
                    "properties": [
                        {
                            "name": "size",
                            "value": "100644466"
                        },
                        {
                            "name": "CreatedBy",
                            "value": "#(nop) ADD file:77be6c657e17932752410ea4e0120f56fcc35fe2d27024e9aba852c8337578db in / "
                        },
                        {
                            "name": "index",
                            "value": "0"
                        }
                    ]
                }
            ]
        }
    ]
}